{"language": "Idris", "core": [{"id": "core-1", "label": "Idris Fundamentals", "description": "Dependently typed functional programming.", "topics": [{"id": "core-1-1", "label": "Installation (Idris 2)", "description": "Install Idris 2. Dependent types let you express invariants in the type system.", "type": "required", "resources": ["https://www.idris-lang.org/", "https://idris2.readthedocs.io/en/latest/tutorial/index.html"]}, {"id": "core-1-2", "label": "Types & Functions", "description": "Type declarations, pattern matching, and totality checking. Types are first-class.", "type": "required", "resources": ["https://idris2.readthedocs.io/en/latest/tutorial/index.html", "https://www.idris-lang.org/"]}, {"id": "core-1-3", "label": "Dependent Types", "description": "Types that depend on values \u2014 Vect n a (vector of exactly n elements). Prove properties in types.", "type": "required", "resources": ["https://idris2.readthedocs.io/en/latest/tutorial/typesfuns.html", "https://www.idris-lang.org/"]}, {"id": "core-1-4", "label": "Interactive Editing", "description": "Type-driven development with holes (?name). The compiler helps you write code.", "type": "required", "resources": ["https://idris2.readthedocs.io/en/latest/tutorial/interactive.html", "https://www.idris-lang.org/"]}, {"id": "core-1-5", "label": "Interfaces (Type Classes)", "description": "interface and implementation for ad-hoc polymorphism.", "type": "required", "resources": ["https://idris2.readthedocs.io/en/latest/tutorial/interfaces.html", "https://www.idris-lang.org/"]}, {"id": "core-1-6", "label": "Totality", "description": "Total functions are guaranteed to terminate. Idris checks totality by default.", "type": "required", "resources": ["https://idris2.readthedocs.io/en/latest/tutorial/index.html", "https://www.idris-lang.org/"]}, {"id": "core-1-7", "label": "Effects & IO", "description": "Algebraic effects for managing side effects. Separate pure from effectful code.", "type": "required", "resources": ["https://idris2.readthedocs.io/en/latest/tutorial/index.html", "https://www.idris-lang.org/"]}, {"id": "core-1-8", "label": "Proofs", "description": "Prove theorems about your code using the type system. Correct by construction.", "type": "advanced", "resources": ["https://idris2.readthedocs.io/en/latest/tutorial/theorems.html", "https://www.idris-lang.org/"]}]}], "paths": [{"id": "path-idris-proofs", "label": "Theorem Proving", "icon": "\u2705", "category": "Verification", "category_icon": "\ud83d\udd2c"}, {"id": "path-idris-effects", "label": "Algebraic Effects", "icon": "\u26a1", "category": "Effects", "category_icon": "\ud83d\udd27"}]}