{"language": "Bash", "path_id": "path-ci-cd-bash", "label": "CI/CD Pipelines", "description": "Bash in CI/CD workflows.", "icon": "\ud83d\udd04", "category": "DevOps", "category_icon": "\u2699\ufe0f", "phases": [{"id": "p1", "label": "CI/CD Pipelines", "description": "Bash in CI/CD workflows.", "topics": [{"id": "p1-1", "label": "GitHub Actions", "description": "Bash steps in .github/workflows/*.yml. Env vars, secrets, artifacts.", "type": "required", "resources": ["https://docs.github.com/en/actions/using-workflows/workflow-syntax-for-github-actions", "https://docs.github.com/en/actions"]}, {"id": "p1-2", "label": "GitLab CI", "description": "script sections in .gitlab-ci.yml. Stages, jobs, and caching.", "type": "required", "resources": ["https://docs.gitlab.com/ee/ci/yaml/", "https://docs.gitlab.com/ee/ci/"]}, {"id": "p1-3", "label": "Build & Test Scripts", "description": "Run tests, build artifacts, and generate reports from CI.", "type": "required", "resources": ["https://docs.github.com/en/actions", "https://docs.gitlab.com/ee/ci/"]}, {"id": "p1-4", "label": "Release Automation", "description": "Tag, changelog, and publish releases with Bash scripts.", "type": "required", "resources": ["https://docs.github.com/en/actions", "https://docs.gitlab.com/ee/ci/"]}]}]}