{"language": "C++", "path_id": "path-unreal-engine", "label": "Unreal Engine", "description": "AAA game engine with C++ and Blueprints.", "icon": "\ud83c\udfae", "category": "Game Development", "category_icon": "\ud83d\udd79\ufe0f", "phases": [{"id": "p1", "label": "Unreal Basics", "description": "Editor, project setup, and C++/Blueprint workflow.", "topics": [{"id": "p1-1", "label": "Editor & Project Setup", "description": "Create a project, navigate the editor, and understand the level/world structure.", "type": "required", "resources": ["https://docs.unrealengine.com/5.3/en-US/understanding-the-basics-of-unreal-engine/", "https://dev.epicgames.com/documentation/en-us/unreal-engine/"]}, {"id": "p1-2", "label": "Actors & Components", "description": "AActor, UActorComponent, and the component-based architecture.", "type": "required", "resources": ["https://docs.unrealengine.com/5.3/en-US/actors-in-unreal-engine/", "https://dev.epicgames.com/documentation/en-us/unreal-engine/"]}, {"id": "p1-3", "label": "Gameplay Framework", "description": "GameMode, PlayerController, Pawn, Character, HUD, GameState.", "type": "required", "resources": ["https://docs.unrealengine.com/5.3/en-US/gameplay-framework-in-unreal-engine/", "https://dev.epicgames.com/documentation/en-us/unreal-engine/"]}, {"id": "p1-4", "label": "UE C++ Macros", "description": "UPROPERTY, UFUNCTION, UCLASS, USTRUCT. Reflection and GC integration.", "type": "required", "resources": ["https://docs.unrealengine.com/5.3/en-US/unreal-engine-reflection-system/", "https://dev.epicgames.com/documentation/en-us/unreal-engine/"]}, {"id": "p1-5", "label": "Blueprints & C++ Integration", "description": "Call C++ from Blueprints and vice versa. BlueprintCallable, BlueprintImplementableEvent.", "type": "required", "resources": ["https://docs.unrealengine.com/5.3/en-US/blueprint-and-cpp-in-unreal-engine/", "https://dev.epicgames.com/documentation/en-us/unreal-engine/"]}, {"id": "p1-6", "label": "Input System", "description": "Enhanced Input System \u2014 Input Actions, Input Mapping Contexts.", "type": "required", "resources": ["https://docs.unrealengine.com/5.3/en-US/enhanced-input-in-unreal-engine/", "https://dev.epicgames.com/documentation/en-us/unreal-engine/"]}]}, {"id": "p2", "label": "Advanced Unreal", "description": "Physics, AI, networking, and packaging.", "topics": [{"id": "p2-1", "label": "Physics & Collision", "description": "Collision profiles, physics bodies, and overlap/hit events.", "type": "required", "resources": ["https://docs.unrealengine.com/5.3/en-US/physics-in-unreal-engine/", "https://dev.epicgames.com/documentation/en-us/unreal-engine/"]}, {"id": "p2-2", "label": "AI (Behavior Trees)", "description": "AI Controllers, Behavior Trees, Blackboards, and EQS.", "type": "required", "resources": ["https://docs.unrealengine.com/5.3/en-US/artificial-intelligence-in-unreal-engine/", "https://dev.epicgames.com/documentation/en-us/unreal-engine/"]}, {"id": "p2-3", "label": "UI (UMG)", "description": "UMG widgets, HUD, menus, and data binding with C++.", "type": "required", "resources": ["https://docs.unrealengine.com/5.3/en-US/umg-ui-designer-for-unreal-engine/", "https://dev.epicgames.com/documentation/en-us/unreal-engine/"]}, {"id": "p2-4", "label": "Materials & Rendering", "description": "Material editor, shaders, post-processing, and Nanite/Lumen.", "type": "optional", "resources": ["https://docs.unrealengine.com/5.3/en-US/materials-in-unreal-engine/", "https://dev.epicgames.com/documentation/en-us/unreal-engine/"]}, {"id": "p2-5", "label": "Networking (Replication)", "description": "Actor replication, RPCs, and multiplayer gameplay.", "type": "optional", "resources": ["https://docs.unrealengine.com/5.3/en-US/networking-and-multiplayer-in-unreal-engine/", "https://dev.epicgames.com/documentation/en-us/unreal-engine/"]}, {"id": "p2-6", "label": "Packaging & Deployment", "description": "Build, cook, and package for Windows, consoles, and mobile.", "type": "required", "resources": ["https://docs.unrealengine.com/5.3/en-US/packaging-unreal-engine-projects/", "https://dev.epicgames.com/documentation/en-us/unreal-engine/"]}]}]}