{"language": "C#", "path_id": "path-azure-sdk", "label": "Azure SDK", "description": "Azure services from .NET.", "icon": "\ud83d\udd37", "category": "Cloud & Azure", "category_icon": "\u2601\ufe0f", "phases": [{"id": "p1", "label": "Azure SDK", "description": "Azure services from .NET.", "topics": [{"id": "p1-1", "label": "Azure.Identity", "description": "DefaultAzureCredential for managed identity and local dev auth.", "type": "required", "resources": ["https://learn.microsoft.com/en-us/dotnet/azure/sdk/authentication/", "https://learn.microsoft.com/en-us/dotnet/azure/"]}, {"id": "p1-2", "label": "Blob Storage", "description": "BlobServiceClient, upload, download, and list blobs.", "type": "required", "resources": ["https://learn.microsoft.com/en-us/azure/storage/blobs/storage-quickstart-blobs-dotnet", "https://learn.microsoft.com/en-us/dotnet/azure/"]}, {"id": "p1-3", "label": "Cosmos DB", "description": "CosmosClient, containers, and LINQ queries against Cosmos DB.", "type": "required", "resources": ["https://learn.microsoft.com/en-us/azure/cosmos-db/nosql/quickstart-dotnet", "https://learn.microsoft.com/en-us/dotnet/azure/"]}, {"id": "p1-4", "label": "Service Bus", "description": "Send and receive messages with Azure Service Bus queues and topics.", "type": "required", "resources": ["https://learn.microsoft.com/en-us/azure/service-bus-messaging/service-bus-dotnet-get-started-with-queues", "https://learn.microsoft.com/en-us/dotnet/azure/"]}]}]}