{"language": "Dart", "path_id": "path-riverpod", "label": "Riverpod", "description": "Reactive state management.", "icon": "\ud83d\udd04", "category": "State Management", "category_icon": "\u2699\ufe0f", "phases": [{"id": "p1", "label": "Riverpod", "description": "Reactive state management.", "topics": [{"id": "p1-1", "label": "Providers", "description": "Provider, StateProvider, FutureProvider, StreamProvider.", "type": "required", "resources": ["https://riverpod.dev/docs/introduction/getting_started", "https://riverpod.dev/"]}, {"id": "p1-2", "label": "ref.watch & ref.read", "description": "Watch for rebuilds, read for one-time access.", "type": "required", "resources": ["https://riverpod.dev/docs/concepts/reading", "https://riverpod.dev/"]}, {"id": "p1-3", "label": "Notifiers", "description": "StateNotifier, AsyncNotifier for complex state logic.", "type": "required", "resources": ["https://riverpod.dev/docs/concepts/providers", "https://riverpod.dev/"]}, {"id": "p1-4", "label": "Code Generation", "description": "@riverpod annotation with riverpod_generator for less boilerplate.", "type": "required", "resources": ["https://riverpod.dev/docs/concepts/about_code_generation", "https://riverpod.dev/"]}]}]}