{"language": "Elixir", "path_id": "path-distillery", "label": "Releases & Deployment", "description": "Production releases and deployment.", "icon": "\ud83d\ude80", "category": "DevOps", "category_icon": "\ud83d\udd27", "phases": [{"id": "p1", "label": "Releases & Deployment", "description": "Production releases and deployment.", "topics": [{"id": "p1-1", "label": "Mix Releases", "description": "mix release for self-contained production builds.", "type": "required", "resources": ["https://hexdocs.pm/mix/Mix.Tasks.Release.html", "https://hexdocs.pm/mix/"]}, {"id": "p1-2", "label": "Runtime Configuration", "description": "runtime.exs and Config.Provider for production config.", "type": "required", "resources": ["https://hexdocs.pm/elixir/Config.html", "https://hexdocs.pm/mix/"]}, {"id": "p1-3", "label": "Docker", "description": "Multi-stage Dockerfile for minimal Elixir production images.", "type": "required", "resources": ["https://hexdocs.pm/phoenix/releases.html", "https://www.phoenixframework.org/"]}, {"id": "p1-4", "label": "Clustering", "description": "libcluster for automatic node discovery and Distributed Erlang.", "type": "optional", "resources": ["https://hexdocs.pm/libcluster/readme.html", "https://github.com/bitwalker/libcluster"]}]}]}