{"language": "Rust", "path_id": "path-actix-web", "label": "Actix Web", "description": "High-performance async web framework.", "icon": "\ud83c\udf10", "category": "Web Frameworks", "category_icon": "\ud83c\udf10", "phases": [{"id": "p1", "label": "Actix Web", "description": "High-performance async web framework.", "topics": [{"id": "p1-1", "label": "App & Routes", "description": "HttpServer, App, web::get/post, extractors (Path, Query, Json).", "type": "required", "resources": ["https://actix.rs/docs/getting-started/", "https://actix.rs/docs/"]}, {"id": "p1-2", "label": "Extractors", "description": "web::Path, web::Query, web::Json, web::Data for request data.", "type": "required", "resources": ["https://actix.rs/docs/extractors/", "https://actix.rs/docs/"]}, {"id": "p1-3", "label": "Middleware", "description": "Logger, authentication, CORS, rate limiting, and custom middleware.", "type": "required", "resources": ["https://actix.rs/docs/middleware/", "https://actix.rs/docs/"]}, {"id": "p1-4", "label": "Error Handling", "description": "Custom error types with ResponseError trait.", "type": "required", "resources": ["https://actix.rs/docs/errors/", "https://actix.rs/docs/"]}, {"id": "p1-5", "label": "State & Database", "description": "web::Data<AppState> for shared state, diesel/sqlx for database.", "type": "required", "resources": ["https://actix.rs/docs/databases/", "https://actix.rs/docs/"]}]}]}