{"language": "TypeScript", "path_id": "path-rxjs", "label": "RxJS", "description": "Reactive Extensions for JavaScript.", "icon": "\ud83d\udd01", "category": "Reactive", "category_icon": "\ud83d\udd04", "phases": [{"id": "p1", "label": "RxJS", "description": "Reactive Extensions for JavaScript.", "topics": [{"id": "p1-1", "label": "Observables", "description": "Observable, of, from, interval, fromEvent. Create async streams.", "type": "required", "resources": ["https://rxjs.dev/guide/observable", "https://rxjs.dev/"]}, {"id": "p1-2", "label": "Operators", "description": "map, filter, switchMap, mergeMap, debounceTime, distinctUntilChanged.", "type": "required", "resources": ["https://rxjs.dev/guide/operators", "https://rxjs.dev/"]}, {"id": "p1-3", "label": "Subjects", "description": "Subject, BehaviorSubject, ReplaySubject for multicasting.", "type": "required", "resources": ["https://rxjs.dev/guide/subject", "https://rxjs.dev/"]}, {"id": "p1-4", "label": "Error & Completion", "description": "catchError, retry, finalize, and takeUntil for cleanup.", "type": "required", "resources": ["https://rxjs.dev/guide/operators", "https://rxjs.dev/"]}]}]}