{"name": "OCaml", "links": {"discord": "https://discord.gg/ocaml", "stackoverflow": "https://stackoverflow.com/questions/tagged/ocaml"}, "tools": [{"name": "opam", "url": "https://opam.ocaml.org/", "desc": "Package manager"}, {"name": "Dune", "url": "https://dune.readthedocs.io/", "desc": "Build system"}, {"name": "Merlin", "url": "https://github.com/ocaml/merlin", "desc": "Editor"}, {"name": "ocamlformat", "url": "https://github.com/ocaml-ppx/ocamlformat", "desc": "Formatter"}], "packages": [{"name": "Dream", "url": "https://aantron.github.io/dream/", "desc": "Web framework"}, {"name": "Lwt", "url": "https://ocsigen.org/lwt/", "desc": "Async"}, {"name": "Core", "url": "https://github.com/janestreet/core", "desc": "Jane Street stdlib"}, {"name": "Alcotest", "url": "https://github.com/mirage/alcotest", "desc": "Testing"}]}